zs_pluginmanager/__init__.py
zs_pluginmanager/manager.py
zs_pluginmanager/plugin.py
zs_pluginmanager/py.typed
zs_pluginmanager/utils.py
ZS_PluginManager-0.0.1.dist-info/LICENSE
ZS_PluginManager-0.0.1.dist-info/METADATA
ZS_PluginManager-0.0.1.dist-info/WHEEL
ZS_PluginManager-0.0.1.dist-info/top_level.txt
ZS_PluginManager-0.0.1.dist-info/RECORD
