Metadata-Version: 2.1
Name: ZS-PluginManager
Version: 0.0.1
Summary: Library to use plugins in Python programs. 
Home-page: https://github.com/Zoynels/ZS-PluginManager
License: GNU Affero General Public License v3
Keywords: plugin,plug-in,manager
Platform: UNKNOWN
Classifier: Intended Audience :: Developers
Classifier: Environment :: Plugins
Classifier: Programming Language :: Python :: 3
Classifier: License :: OSI Approved :: GNU Affero General Public License v3
Requires-Dist: entrypoints (>=0.3)
